setuptools_scm_patch.py
setuptools_scm_patch-1.0.1.dist-info/METADATA
setuptools_scm_patch-1.0.1.dist-info/WHEEL
setuptools_scm_patch-1.0.1.dist-info/top_level.txt
setuptools_scm_patch-1.0.1.dist-info/RECORD
