Metadata-Version: 2.4
Name: setuptools-scm-patch
Version: 1.0.1
Summary: A tiny patch for setuptools_scm to customize version formatting.
Requires-Python: >=3
